findd/__about__.py
findd/__init__.py
findd/model.py
findd/queue.py
findd/services.py
findd/cli/__init__.py
findd/cli/__main__.py
findd/cli/commands.py
findd/cli/context.py
findd/cli/parser.py
findd/cli/views.py
findd/cli/widgets.py
findd/utils/__init__.py
findd/utils/crypto.py
findd/utils/format.py
findd/utils/path.py
findd/utils/progress.py
tests/__init__.py
tests/test_services.py
tests/cli/__init__.py
tests/cli/test__init__.py
tests/utils/__init__.py
tests/utils/test_crypto.py
tests/utils/test_format.py
tests/utils/test_path.py
findd-0.9.3.dist-info/LICENSE
findd-0.9.3.dist-info/METADATA
findd-0.9.3.dist-info/WHEEL
findd-0.9.3.dist-info/entry_points.txt
findd-0.9.3.dist-info/top_level.txt
findd-0.9.3.dist-info/RECORD
