Metadata-Version: 2.1
Name: findd
Version: 0.9.3
Summary: Find duplicate files, based on size and hashvalues.
Home-page: https://github.com/schnittstabil/findd
Author: Michael Mayer
Author-email: michael@schnittstabil.de
License: MIT
Keywords: find duplicates cli database-assisted
Platform: any
Classifier: Development Status :: 4 - Beta
Classifier: Intended Audience :: System Administrators
Classifier: Topic :: System :: Archiving :: Backup
Classifier: License :: OSI Approved :: MIT License
Classifier: Programming Language :: Python :: 3
Requires-Python: >=3.6
Requires-Dist: SQLAlchemy (==1.4.7)
Requires-Dist: blinker (==1.4)
Requires-Dist: progressbar2 (==3.53.1)
Requires-Dist: wheel
